{"stats": {"physical base weapon damage": "51~52", "move speed": "-30", "allstats": "Physical Base Weapon Damage,Move Speed"}, "abilities": {"Primary": {"Attack 1": {"damagetype": "Slash", "combodamage": "100%", "hitstopduration": 0.2, "movementmultiplier": "65%", "preparemovementmultiplier": "82.5%", "impactzones": ["100%", "70%"], "impactpower": "4", "effects": {"AttackHit1": {"rarity": {"Global": {"Scaling": "100%"}}}, "AttackHit2": {"rarity": {"Global": {"Scaling": "100%"}}}, "HitSlow": {"rarity": {"Global": {"Duration": "1.0", "Move Speed Bonus": "-30%"}}}}}}, "Other": {"Unique Passive": {"effects": {"UniqueSoulAbsorption": {"rarity": {"Global": {"Duration": "12.0", "Strength": "5", "Vigor": "5"}}}}}}}, "categories": {"Weapon": "True"}, "types": {"Axe": "Weapon"}, "hitbox": {"height": 56.51, "width": 13.29, "depth": 2.18}, "rarities": ["8"], "handtype": "Two Handed", "slottype": "Main-Hand", "haspassive": true, "isartifact": true, "isminiartifact": false, "artifactname": "", "artifactpower": "Successful weapon attacks absorb the opponent's soul to gain 5 [[Stats#Strength|Strength]] and [[Stats#Vigor|Vigor]] for 12 seconds, stacking up to 3 times and refreshing on each new stack.", "artifacttags": {}, "invwidth": 2, "invheight": 4, "invslots": "[[File:2x4InvSlot.jpg]]", "flavortext": "Through a bond that transcended realms, a guardian of souls granted a mortal companion this enchanted axe.", "maxammocount": 0, "maxcount": 1, "maxcontentscount": "", "reloadtime": "", "wearingdelaytime": 0, "equiptime": "", "unequiptime": "", "ap": {"8": 80}, "apexception": {}, "xp": {"8": 7}, "xpexception": {"8": 7}, "gearscore": {"0": 0, "1": 0, "2": 0, "3": 0, "4": 0, "5": 0, "6": 0, "7": 0, "8": 130}, "gearscoreexception": {"8": 130}, "isprojectile": false, "initialspeed": "", "damagefalloff": "", "piercecount": "", "classesbackend": ["Barbarian"], "classes": ["[[Barbarian]]"], "impactresistance": "", "iscraftableby": "", "interactiontime": "", "interactiontimescaling": "", "actiontime": "", "actiontimescaling": "", "animationtimes": {"Primary": {"Attack 1": {"Animation Time": 2.7, "Windup": 0.7, "Hit": 0.156, "Finish": 1.844, "Next Attack": "Reset", "hit with hitstop": 0.356}}, "Other": {}}, "id": "Soulscraper", "baseid": "FellingAxe", "bpid": "FellingAxe", "name": "Soulscraper", "originbaseid": "Felling Axe", "originname": "Felling Axe", "sellprices": {"8": 1000}, "incraftingrecipefor": "", "questinformation": "", "numenchants": {"8": 6}, "dropSourceTable": {}}